{"questions":[{"id":621902,"description":"<p>Отобрать корни на отрезке \\(\\left[10\\pi;\\ \\dfrac{23\\pi}{2}\\right]\\) из серий решений \\(x = \\dfrac{3\\pi}{4} + \\pi k;\\ x = \\pi k,\\ k \\in Z\\).</p>","type_id":"scan","files":[],"points":1,"order_id":1,"criterions":null,"number":13,"time_seconds":null,"exam_topic":null,"difficulty":1,"markup":[{"id":498,"title":"13.1 Замена","subtopics":[]}],"answer":{"id":5668184821,"homework_question_id":621902,"answer":[],"is_correct":false,"points":0,"files":[{"id":13820651,"mime":"image/png","name":"изображение_2024-11-25_180713370.png","extension":"png","link":"https://storage.yandexcloud.net/topschool.backet/public/homework_question_files/d8794e85-28db-421d-b3ab-33b69d56712c.png"}],"is_validate":true,"showRightAnswer":false,"showCuratorComment":true,"showExplanation":true,"right_answer":[],"question_comment":"<figure class=\"image image_resized\" style=\"width:48.75%;\"><img src=\"https://storage.yandexcloud.net/topschool.backet/public/html_editor/47544f8e-0d0b-4237-aa63-d49d30712117.png\"></figure><p>$$x_1 = 11\\pi \\\\ x_2 = 11\\pi - \\dfrac{\\pi}{4} = \\dfrac{44\\pi - \\pi}{4} = \\dfrac{43\\pi}{4} \\\\ x_3 = 10\\pi$$</p><p>Ответ: а\\()\\ x = \\dfrac{3\\pi}{4} + \\pi k;\\ x = \\pi k,\\ k \\in Z\\); б\\()\\ 11\\pi;\\ \\dfrac{43\\pi}{4};\\ 10\\pi\\).</p>","explanation_files":[],"video_link":null,"comment":"<p><img src=\"https://storage.yandexcloud.net/topschool.backet/public/comment_files/4b5e07a9-1791-4b92-9e59-344e321ae09d.png\" style=\"width: 334px;\"><br>Не обозначены крайние точки промежутка на окружности</p>","comment_files":[],"max_tries":null,"current_try":null,"can_submit":true,"showRightByCond":true}},{"id":621903,"description":"<p>Отобрать корни на отрезке \\(\\left[\\dfrac{5\\pi}{2};\\ 4\\pi\\right]\\) из серий решений \\(x = \\pm \\dfrac{\\pi}{6} + 2\\pi k,\\ k \\in Z\\).</p>","type_id":"scan","files":[],"points":1,"order_id":2,"criterions":null,"number":13,"time_seconds":null,"exam_topic":null,"difficulty":1,"markup":[{"id":498,"title":"13.1 Замена","subtopics":[]}],"answer":{"id":5668184839,"homework_question_id":621903,"answer":[],"is_correct":false,"points":0,"files":[{"id":13820660,"mime":"image/png","name":"изображение_2024-11-25_180725870.png","extension":"png","link":"https://storage.yandexcloud.net/topschool.backet/public/homework_question_files/14b282c3-f068-4aa3-bdd2-ea1f98e6081a.png"}],"is_validate":true,"showRightAnswer":false,"showCuratorComment":true,"showExplanation":true,"right_answer":[],"question_comment":"<figure class=\"image image_resized\" style=\"width:47.58%;\"><img src=\"https://storage.yandexcloud.net/topschool.backet/public/html_editor/bbfc5283-7d52-4e37-bab9-cc6c5c9662b9.png\"></figure><p>$$x_1 = 4\\pi - \\dfrac{\\pi}{6} = \\dfrac{24\\pi - \\pi}{6} = \\dfrac{23\\pi}{6}$$</p><p>Ответ: а\\()\\ x = \\pm \\dfrac{\\pi}{6} + 2\\pi k,\\ k \\in Z\\); б\\()\\ \\dfrac{23\\pi}{6}\\)</p>","explanation_files":[],"video_link":null,"comment":"<p><img src=\"https://storage.yandexcloud.net/topschool.backet/public/comment_files/cb6cf060-b9c9-4268-851e-f52f09a46299.png\" style=\"width: 372px;\"><br>Не обозначены крайние точки промежутка на окружности</p>","comment_files":[],"max_tries":null,"current_try":null,"can_submit":true,"showRightByCond":true}},{"id":621904,"description":"<p>Отобрать корни на отрезке \\(\\left[\\dfrac{3\\pi}{2};\\ 3\\pi\\right]\\) из серий решений \\(x = -\\dfrac{\\pi}{6} + \\dfrac{\\pi k}{2},\\ k \\in Z\\).</p>","type_id":"scan","files":[],"points":1,"order_id":3,"criterions":null,"number":13,"time_seconds":null,"exam_topic":null,"difficulty":1,"markup":[{"id":498,"title":"13.1 Замена","subtopics":[]}],"answer":{"id":5668184857,"homework_question_id":621904,"answer":[],"is_correct":false,"points":0,"files":[{"id":13820669,"mime":"image/png","name":"изображение_2024-11-25_180739483.png","extension":"png","link":"https://storage.yandexcloud.net/topschool.backet/public/homework_question_files/6db79263-a7f1-4443-9093-9c0a5cf1e722.png"}],"is_validate":true,"showRightAnswer":false,"showCuratorComment":true,"showExplanation":true,"right_answer":[],"question_comment":"<figure class=\"image image_resized\" style=\"width:50.59%;\"><img src=\"https://storage.yandexcloud.net/topschool.backet/public/html_editor/6f414c43-0eea-4dfa-8f1c-f66883dac78b.png\"></figure><p>$$x_1 = 2\\pi - \\dfrac{\\pi}{6} = \\dfrac{12\\pi- \\pi}{6} = \\dfrac{11\\pi}{6} \\\\ x_2 = 2\\pi + \\dfrac{\\pi}{3} = \\dfrac{7\\pi}{3} \\\\ x_3 = 3\\pi - \\dfrac{\\pi}{6} = \\dfrac{17\\pi}{6}$$</p><p>Ответ: а\\()\\ x = -\\dfrac{\\pi}{6} + \\dfrac{\\pi k}{2},\\ k \\in Z\\); б\\()\\ \\dfrac{11\\pi}{6};\\ \\dfrac{7\\pi}{3};\\ \\dfrac{17\\pi}{6}\\)</p>","explanation_files":[],"video_link":null,"comment":"<p><img src=\"https://storage.yandexcloud.net/topschool.backet/public/comment_files/103c9b5d-09a6-4771-b886-deadc6161241.png\" style=\"width: 334px;\"><br>Не обозначены крайние точки промежутка на окружности</p>","comment_files":[],"max_tries":null,"current_try":null,"can_submit":true,"showRightByCond":true}},{"id":621905,"description":"<p>Отобрать корни на отрезке \\(\\left[-2\\pi;\\ -\\dfrac{\\pi}{2}\\right]\\) из серий решений \\(\\left[ \\begin{array}{l l}<br>x=-arctg\\ 2+\\pi k,\\ k\\in Z\\\\<br>x=-arctg\\ 3+\\pi k,\\ k\\in Z<br>\\end{array} \\right.\\).</p>","type_id":"scan","files":[],"points":1,"order_id":4,"criterions":null,"number":13,"time_seconds":null,"exam_topic":null,"difficulty":1,"markup":[{"id":498,"title":"13.1 Замена","subtopics":[]}],"answer":{"id":5668184872,"homework_question_id":621905,"answer":[],"is_correct":false,"points":0,"files":[{"id":13820686,"mime":"image/png","name":"изображение_2024-11-25_180804155.png","extension":"png","link":"https://storage.yandexcloud.net/topschool.backet/public/homework_question_files/e2f6a510-de65-4d87-ba7a-e2a5cbe91b1d.png"}],"is_validate":true,"showRightAnswer":false,"showCuratorComment":true,"showExplanation":true,"right_answer":[],"question_comment":"<figure class=\"image image_resized\" style=\"width:51.47%;\"><img src=\"https://storage.yandexcloud.net/topschool.backet/public/html_editor/18b6b62c-f163-430f-9920-f51797a4616a.png\"></figure><p>$$x_1 = -\\pi - arctg\\ 2 \\\\ x_2 = -\\pi - arctg\\ 3$$</p><p>Ответ: а\\()\\ -arctg\\ 2+\\pi k;\\ -arctg\\ 3+\\pi k,\\ k\\in Z\\); б\\()\\ -\\pi - arctg\\ 2;\\ -\\pi - arctg\\ 3\\)</p>","explanation_files":[],"video_link":null,"comment":"<p><img src=\"https://storage.yandexcloud.net/topschool.backet/public/comment_files/ef99275b-900b-4f42-a281-f73f686dc483.png\" style=\"width: 365px;\"><br>Не обозначены крайние точки промежутка на окружности</p>","comment_files":[],"max_tries":null,"current_try":null,"can_submit":true,"showRightByCond":true}},{"id":621906,"description":"<p>Отобрать корни на отрезке \\(\\left[-\\dfrac{5\\pi}{2};\\ -\\pi\\right]\\) из серий решений \\(x = \\dfrac{\\pi}{2} + 2\\pi k;\\ x = \\dfrac{\\pi}{6} + 2\\pi k;\\ x = \\dfrac{5\\pi}{6} + 2\\pi k,\\ k \\in Z\\).</p>","type_id":"scan","files":[],"points":1,"order_id":5,"criterions":null,"number":13,"time_seconds":null,"exam_topic":null,"difficulty":1,"markup":[{"id":498,"title":"13.1 Замена","subtopics":[]}],"answer":{"id":5668184887,"homework_question_id":621906,"answer":[],"is_correct":false,"points":0,"files":[{"id":13820711,"mime":"image/png","name":"изображение_2024-11-25_180841801.png","extension":"png","link":"https://storage.yandexcloud.net/topschool.backet/public/homework_question_files/062a9e5c-74db-4dc1-bddf-ef7e7120637e.png"}],"is_validate":true,"showRightAnswer":false,"showCuratorComment":true,"showExplanation":true,"right_answer":[],"question_comment":"<figure class=\"image image_resized\" style=\"width:50.15%;\"><img src=\"https://storage.yandexcloud.net/topschool.backet/public/html_editor/b277fb6e-8610-45de-b3f6-de23c01a6501.png\"></figure><p>$$x_1 = -\\pi - \\dfrac{\\pi}{6} = -\\dfrac{7\\pi}{6} \\\\ x_2 = -\\dfrac{3\\pi}{2} \\\\ x_3 = -2\\pi + \\dfrac{\\pi}{6} = -\\dfrac{11\\pi}{6}$$</p><p>Ответ: а\\()\\ x = \\dfrac{\\pi}{2} + 2\\pi k;\\ \\dfrac{\\pi}{6} + 2\\pi k;\\ x = \\dfrac{5\\pi}{6} + 2\\pi k,\\ k \\in Z\\); б\\()\\ -\\dfrac{7\\pi}{6};\\ -\\dfrac{3\\pi}{2};\\ -\\dfrac{11\\pi}{6}\\)</p>","explanation_files":[],"video_link":null,"comment":"<p><img src=\"https://storage.yandexcloud.net/topschool.backet/public/comment_files/0c69884f-f2a7-4006-91a1-eee152bb94d3.png\" style=\"width: 297px;\"><br>Не обозначены крайние точки промежутка на окружности</p>","comment_files":[],"max_tries":null,"current_try":null,"can_submit":true,"showRightByCond":true}},{"id":621907,"description":"<p>Отобрать корни на отрезке \\(\\left(-\\pi;\\ \\dfrac{\\pi}{2}\\right)\\) из серий решений \\(x = \\dfrac{\\pi}{10} + \\dfrac{\\pi k}{5};\\ x = \\pm \\dfrac{\\pi}{6} + \\pi k,\\ k \\in Z\\).</p>","type_id":"scan","files":[],"points":1,"order_id":6,"criterions":null,"number":13,"time_seconds":null,"exam_topic":null,"difficulty":1,"markup":[{"id":498,"title":"13.1 Замена","subtopics":[]}],"answer":{"id":5668184902,"homework_question_id":621907,"answer":[],"is_correct":false,"points":0,"files":[{"id":13820732,"mime":"image/png","name":"изображение_2024-11-25_180909384.png","extension":"png","link":"https://storage.yandexcloud.net/topschool.backet/public/homework_question_files/68769438-d56b-4999-bff3-8ab9dbba1ae6.png"}],"is_validate":true,"showRightAnswer":false,"showCuratorComment":true,"showExplanation":true,"right_answer":[],"question_comment":"<figure class=\"image image_resized\" style=\"width:51.63%;\"><img src=\"https://storage.yandexcloud.net/topschool.backet/public/html_editor/7c585b49-a612-4c67-8074-0ebc748bb1bd.png\"></figure><p>$$x_1 = \\dfrac{\\pi}{10} + \\dfrac{\\pi}{5} = \\dfrac{3\\pi}{10} \\\\ x_2 = \\dfrac{\\pi}{6} \\\\ x_3 = \\dfrac{\\pi}{10} \\\\ x_4 = -\\dfrac{\\pi}{10} \\\\ x_5 = -\\dfrac{\\pi}{6} \\\\ x_6 = -\\dfrac{\\pi}{10} - \\dfrac{\\pi}{5} = -\\dfrac{3\\pi}{10} \\\\ x_7 = -\\dfrac{\\pi}{2} \\\\ x_8 = -\\dfrac{\\pi}{2} - \\dfrac{\\pi}{5} = -\\dfrac{5\\pi + 2\\pi}{10} = -\\dfrac{7\\pi}{10} \\\\ x_9 = -\\pi + \\dfrac{\\pi}{6} = -\\dfrac{5\\pi}{6} \\\\ x_{10} = -\\pi + \\dfrac{\\pi}{10} = -\\dfrac{9\\pi}{10}$$</p><p>Ответ: а\\()\\ x = \\dfrac{\\pi}{10} + \\dfrac{\\pi k}{5};\\ x = \\pm \\dfrac{\\pi}{6} + \\pi k,\\ k \\in Z\\);&nbsp;</p><p>б\\()\\ \\dfrac{3\\pi}{10};\\ \\dfrac{\\pi}{6};\\ \\dfrac{\\pi}{10};\\ -\\dfrac{\\pi}{10};\\ -\\dfrac{\\pi}{6};\\ -\\dfrac{3\\pi}{10};\\ -\\dfrac{\\pi}{2};\\ -\\dfrac{7\\pi}{10};\\ -\\dfrac{5\\pi}{6};\\ -\\dfrac{9\\pi}{10}\\)</p>","explanation_files":[],"video_link":null,"comment":"<p><img src=\"https://storage.yandexcloud.net/topschool.backet/public/comment_files/538445b0-5406-4348-b40a-2ff7b625d8d2.png\" style=\"width: 488px;\"><img src=\"https://storage.yandexcloud.net/topschool.backet/public/comment_files/c05b8cd2-ee37-45e5-ac49-ff578727a079.png\" style=\"width: 488px;\"><br>Тут несколько арифметических ошибок</p>","comment_files":[],"max_tries":null,"current_try":null,"can_submit":true,"showRightByCond":true}},{"id":621908,"description":"<p>а\\()\\) Решите уравнение \\(\\cos 2x-5\\sqrt{2}\\cos x-5=0\\).</p><p>б\\()\\) Укажите корни этого уравнения, принадлежащие отрезку \\(\\left[ -3\\pi ;-\\dfrac{3\\pi }{2}\\right]\\).</p>","type_id":"scan","files":[],"points":2,"order_id":7,"criterions":null,"number":13,"time_seconds":null,"exam_topic":null,"difficulty":1,"markup":[{"id":500,"title":"13.3 Формулы тригонометрии","subtopics":[]}],"answer":{"id":5668184923,"homework_question_id":621908,"answer":[],"is_correct":false,"points":0,"files":[{"id":13820739,"mime":"image/png","name":"изображение_2024-11-25_180919374.png","extension":"png","link":"https://storage.yandexcloud.net/topschool.backet/public/homework_question_files/538b7a8b-65bb-4cad-8dc7-75172345d0dd.png"},{"id":13820744,"mime":"image/png","name":"изображение_2024-11-25_180924585.png","extension":"png","link":"https://storage.yandexcloud.net/topschool.backet/public/homework_question_files/ce1fad19-e774-499c-9d69-6d5a85baaa31.png"}],"is_validate":true,"showRightAnswer":false,"showCuratorComment":true,"showExplanation":true,"right_answer":[],"question_comment":"<p>$$\\cos 2x-5\\sqrt{2}\\cos x-5=0 \\\\ 2\\cos^2 x - 1 - 5\\sqrt2 \\cos x - 5 = 0 \\\\ 2\\cos^2 x - 5\\sqrt2 \\cos x - 6 = 0$$</p><p>Пусть \\(\\cos x = t\\), тогда:</p><p>$$2t^2 - 5\\sqrt2 t - 6 = 0 \\\\ \\left[ \\begin{array}{l l}<br>t_{1} =3\\sqrt{2}\\\\<br>t_{2} =-\\dfrac{\\sqrt{2}}{2}<br>\\end{array} \\right.$$</p><p>Обратная замена: $$\\cos x = -\\dfrac{\\sqrt2}{2} \\\\ \\Rightarrow x = \\pm \\dfrac{3\\pi}{4} + 2\\pi k,\\ k \\in Z$$</p><p>\\(\\cos x = 3\\sqrt2\\) не имеет решений, т.к. \\(\\cos x \\in [-1; 1]\\).</p><p>&nbsp;</p><p>б) Отберем корни с помощью числовой окружности на отрезке \\(\\left[ -3\\pi ;-\\dfrac{3\\pi }{2}\\right]\\):</p><figure class=\"image image_resized\" style=\"width:46.89%;\"><img src=\"https://storage.yandexcloud.net/topschool.backet/public/html_editor/01620e88-f900-41bd-a69a-09187c2734f8.png\"></figure><p>$$x_1 = -3\\pi + \\dfrac{\\pi}{4} = -\\dfrac{11\\pi}{4}$$</p><p>Ответ: а\\()\\ \\pm \\dfrac{3\\pi}{4} + 2\\pi k,\\ k \\in Z\\); б\\()\\ -\\dfrac{11\\pi}{4}\\)</p>","explanation_files":[],"video_link":null,"comment":"<p><img src=\"https://storage.yandexcloud.net/topschool.backet/public/comment_files/319ecd4b-88cc-470e-beb0-f570c289d7ff.png\" style=\"width: 273px;\"><br>Пиши \"Не подходит\"<br><br><img src=\"https://storage.yandexcloud.net/topschool.backet/public/comment_files/8e290dd9-d559-4ba7-8307-58064d753780.png\" style=\"width: 25%;\"><br>Не обозначены крайние точки промежутка на окружности</p>","comment_files":[],"max_tries":null,"current_try":null,"can_submit":true,"showRightByCond":true}},{"id":621909,"description":"<p>Решите уравнение \\(4\\sin^2 x = tg\\ x\\).</p>","type_id":"scan","files":[],"points":1,"order_id":8,"criterions":null,"number":13,"time_seconds":null,"exam_topic":null,"difficulty":1,"markup":[{"id":501,"title":"13.4 Ограничения","subtopics":[]}],"answer":{"id":5668184941,"homework_question_id":621909,"answer":[],"is_correct":true,"points":1,"files":[{"id":13820753,"mime":"image/png","name":"изображение_2024-11-25_180932125.png","extension":"png","link":"https://storage.yandexcloud.net/topschool.backet/public/homework_question_files/aec7fc2a-fe00-4d4a-8e1a-c5ce9dc7d88d.png"}],"is_validate":true,"showRightAnswer":false,"showCuratorComment":true,"showExplanation":true,"right_answer":[],"question_comment":"<p>Так как в уравнении присутствует тангенс, то \\(\\cos x \\neq 0\\ \\Leftrightarrow\\ x \\neq \\dfrac{\\pi}{2} + \\pi n,\\ n \\in Z\\). После введения таких ограничений исходное уравнение можно умножить на \\(\\cos x\\):</p><p>$$4\\sin^2 x = tg\\ x \\\\ 4\\cos x \\sin^2 x = \\sin x \\\\ \\sin x(4\\cos x \\sin x - 1) = 0 \\\\ \\sin x(2\\sin 2x - 1) = 0 \\\\ \\left[ \\begin{array}{l l}<br>\\sin x=0\\\\<br>\\sin 2x=\\dfrac{1}{2}<br>\\end{array} \\right. \\\\ \\left[ \\begin{array}{l l}<br>x=\\pi k,\\ k\\in Z\\\\<br>2x=\\dfrac{\\pi }{6} +2\\pi k,\\ k\\in Z\\\\<br>2x=\\dfrac{5\\pi }{6} +2\\pi k,\\ k\\in Z<br>\\end{array} \\right. \\\\ \\Rightarrow\\ \\left[ \\begin{array}{l l}<br>x=\\pi k,\\ k\\in Z\\\\<br>x=\\dfrac{\\pi }{12} +\\pi k,\\ k\\in Z\\\\<br>x=\\dfrac{5\\pi }{12} +\\pi k,\\ k\\in Z<br>\\end{array} \\right.$$</p><p>Ответ: \\(\\pi k;\\ \\dfrac{\\pi }{12} +\\pi k;\\ \\dfrac{5\\pi }{12} +\\pi k,\\ k\\in Z\\)</p>","explanation_files":[],"video_link":null,"comment":"<p>Верно!</p>","comment_files":[],"max_tries":null,"current_try":null,"can_submit":true,"showRightByCond":true}},{"id":621910,"description":"<p>Решите уравнение \\(\\sin x(2\\sin x - 3\\ ctg\\ x) = 3\\).</p>","type_id":"scan","files":[],"points":1,"order_id":9,"criterions":null,"number":13,"time_seconds":null,"exam_topic":null,"difficulty":1,"markup":[{"id":501,"title":"13.4 Ограничения","subtopics":[]}],"answer":{"id":5668184955,"homework_question_id":621910,"answer":[],"is_correct":true,"points":1,"files":[{"id":13820758,"mime":"image/png","name":"изображение_2024-11-25_180938867.png","extension":"png","link":"https://storage.yandexcloud.net/topschool.backet/public/homework_question_files/5142431c-09cb-4186-9dd1-bd883aae9d95.png"}],"is_validate":true,"showRightAnswer":false,"showCuratorComment":true,"showExplanation":true,"right_answer":[],"question_comment":"<p>Так как в уравнении присутствует котангенс, то \\(\\sin x \\neq 0\\ \\Leftrightarrow\\ x \\neq \\pi n,\\ n \\in Z\\).</p><p>$$\\sin x(2\\sin x - 3\\ ctg\\ x) = 3 \\\\ 2\\sin^2 x - 3\\cos x = 3 \\\\ 2(1 - \\cos^2 x) - 3\\cos x - 3 = 0 \\\\ 2\\cos^2 x + 3\\cos x + 1 = 0 \\\\ \\left[ \\begin{array}{l l}<br>\\cos x=-1\\\\<br>\\cos x=-\\dfrac{1}{2}<br>\\end{array} \\right. \\\\ \\Rightarrow\\ \\left[ \\begin{array}{l l}<br>x_{1} =\\pi +2\\pi k,\\ k\\in Z\\\\<br>x_{2} =\\pm \\dfrac{2\\pi }{3} +2\\pi k,\\ k\\in Z<br>\\end{array} \\right.$$<br>Первая серия корней не удовлетворяет ограничениям, значит в ответ идет только вторая.&nbsp;</p><p>&nbsp;</p><p>Ответ: \\(\\pm \\dfrac{2\\pi }{3} +2\\pi k,\\ k\\in Z\\)</p>","explanation_files":[],"video_link":null,"comment":"<p>Верно!</p>","comment_files":[],"max_tries":null,"current_try":null,"can_submit":true,"showRightByCond":true}},{"id":621911,"description":"<p>Решите уравнение \\(1-4\\cos^{2}\\left( x-\\dfrac{5\\pi }{12}\\right) =\\sqrt{3}\\cos 2x\\).</p>","type_id":"scan","files":[],"points":1,"order_id":10,"criterions":null,"number":13,"time_seconds":null,"exam_topic":null,"difficulty":1,"markup":[{"id":500,"title":"13.3 Формулы тригонометрии","subtopics":[]}],"answer":{"id":5668184974,"homework_question_id":621911,"answer":[],"is_correct":false,"points":0,"files":[{"id":13820761,"mime":"image/png","name":"изображение_2024-11-25_180947166.png","extension":"png","link":"https://storage.yandexcloud.net/topschool.backet/public/homework_question_files/6fb5113e-a496-4d20-8cc7-aae982242103.png"}],"is_validate":true,"showRightAnswer":false,"showCuratorComment":true,"showExplanation":true,"right_answer":[],"question_comment":"<p>$$2\\left(1 - 2\\cos^2 \\left(x - \\dfrac{5\\pi}{12}\\right)\\right) - 1 = \\sqrt3 \\cos 2x$$</p><p>По формуле косинуса двойного угла: \\(\\cos 2\\alpha = \\cos^2 \\alpha - \\sin^2 \\alpha = \\cos^2 \\alpha - (1 - \\cos^2 \\alpha) = &nbsp;2\\cos^2 \\alpha - 1\\).</p><p>$$-2\\cos \\left(2x - \\dfrac{5\\pi}{6}\\right) - 1 - \\sqrt3 \\cos 2x = 0$$</p><p>По формуле косинуса разности: \\(\\cos(\\alpha - \\beta) = \\cos \\alpha \\cos \\beta + \\sin \\alpha \\sin \\beta\\).</p><p>$$-2 \\left(\\cos 2x \\cos \\dfrac{5\\pi}{6} + \\sin 2x \\sin \\dfrac{5\\pi}{6}\\right) - 1 - \\sqrt3 \\cos 2x = 0 \\\\ \\dfrac{2\\sqrt3}{2} \\cos 2x - \\dfrac{2}{2}\\sin 2x - 1 - \\sqrt3\\cos 2x = 0 \\\\ \\sqrt3 \\cos 2x - \\sin 2x - 1 - \\sqrt3\\cos 2x = 0 \\\\ \\Rightarrow\\ \\sin 2x = -1 \\\\ 2x = -\\dfrac{\\pi}{2} + 2\\pi n,\\ n \\in Z \\\\ x = -\\dfrac{\\pi}{4} + \\pi n,\\ n \\in Z$$</p><p>Ответ: \\(-\\dfrac{\\pi}{4} + \\pi n,\\ n \\in Z\\)</p>","explanation_files":[],"video_link":"https://www.youtube.com/live/ku0y_f1IExk?si=XV98NTzw3u_JCHXa&t=5963","comment":"<p><img src=\"https://storage.yandexcloud.net/topschool.backet/public/comment_files/e634a3c1-5981-45a4-8eb6-f2990669fe55.png\" style=\"width: 25%;\"><br>В этом переходе потерян знак в действии, которое ты делал в уме</p>","comment_files":[],"max_tries":null,"current_try":null,"can_submit":true,"showRightByCond":true}}],"mistakes":[{"id":615296,"description":"<p>Фабрика выпускает сумки. В среднем на \\(150\\) качественных сумок приходится \\(14\\) сумок со скрытыми дефектами. Найдите вероятность того, что купленная сумка окажется качественной. Результат округлите до сотых.</p>","type_id":"writing_words","points":1,"is_case_insensitive":false,"files":[],"order_id":27,"number":4,"time_seconds":null,"exam_topic":null,"difficulty":1,"markup":[{"id":442,"title":"4.1 Классическое определение вероятности","subtopics":[]}],"answer":{"id":7710222,"homework_question_id":615296,"answer":["0,91"],"is_correct":true,"points":1,"comment":null,"files":[],"is_validate":true,"max_tries":null,"current_try":null,"can_submit":true}},{"id":615356,"description":"<p>Найдите значение выражения \\(2\\sqrt{2}\\cos^2\\dfrac{3\\pi}{8}-\\sqrt{2}\\).</p>","type_id":"writing_words","points":1,"is_case_insensitive":false,"files":[],"order_id":62,"number":7,"time_seconds":null,"exam_topic":null,"difficulty":1,"markup":[{"id":455,"title":"7.2 Тригонометрические формулы двойного угла","subtopics":[]}],"answer":{"id":7710585,"homework_question_id":615356,"answer":["-1"],"is_correct":true,"points":1,"comment":null,"files":[],"is_validate":true,"max_tries":null,"current_try":null,"can_submit":true}},{"id":615413,"description":"<p>Найдите \\(\\mathrm{tg} \\, \\alpha\\), если \\(\\cos\\alpha=\\dfrac{5\\sqrt{26}}{26}\\) и \\(\\alpha \\in \\left(0; \\dfrac{\\pi}{2}\\right)\\).</p>","type_id":"writing_words","points":1,"is_case_insensitive":false,"files":[],"order_id":68,"number":7,"time_seconds":null,"exam_topic":null,"difficulty":1,"markup":[{"id":457,"title":"7.4 Тригонометрические тождества","subtopics":[]}],"answer":{"id":7710778,"homework_question_id":615413,"answer":["0,2"],"is_correct":true,"points":1,"comment":null,"files":[],"is_validate":true,"max_tries":null,"current_try":null,"can_submit":true}},{"id":615464,"description":"<p>На рисунке изображен график функции вида \\(f(x)=ax^2+bx+c\\), где числа \\(a\\), \\(b\\) и \\(c\\) – целые. Найдите значение \\(f(11)\\).</p><figure class=\"image image_resized\" style=\"width:50.58%;\"><img src=\"https://storage.yandexcloud.net/topschool.backet/public/html_editor/405a9ce8-6779-4ca1-b139-4cc808be7b93.png\"></figure>","type_id":"writing_words","points":1,"is_case_insensitive":false,"files":[],"order_id":106,"number":11,"time_seconds":null,"exam_topic":null,"difficulty":1,"markup":[{"id":487,"title":"11.2 Квадратичная функция","subtopics":[]}],"answer":{"id":7711072,"homework_question_id":615464,"answer":["78"],"is_correct":true,"points":1,"comment":null,"files":[],"is_validate":true,"max_tries":null,"current_try":null,"can_submit":true}}]}