{"title":"Урок №39. Номер 10. Текстовые задачи","homeworks":[12273407],"blocks":[{"id":131056,"type_id":"webinar","order_id":1,"status":"published","data":{"id":50558,"description":"https://rutube.ru/video/private/7d48fb2512bcb849a4e1806283a86d3f/?p=8RRTapE7AHPVDEmSkZmQ9g","youtube_link":"https://youtu.be/PSc_iizhtSM","rutube_link":"https://rutube.ru/video/private/7d48fb2512bcb849a4e1806283a86d3f/?p=8RRTapE7AHPVDEmSkZmQ9g","kinescope_link":null,"properties":{"chat_exist":false}}},{"id":131057,"type_id":"content","order_id":3,"status":"published","data":{"id":37125,"links":[{"link":"https://t.me/Control100b_bot","description":"Бот для отметки посещений онлайн"}],"files":[{"id":14405480,"mime":"application/pdf","name":"Легион. Список задач к 39 уроку.pdf","extension":"pdf","link":"https://storage.yandexcloud.net/topschool.backet/public/content_file/67370955-b3f3-412c-9915-160f976e2557.pdf"},{"id":14405497,"mime":"application/pdf","name":"Легион. Урок 39. Класс.pdf","extension":"pdf","link":"https://storage.yandexcloud.net/topschool.backet/public/content_file/8c5e7ec8-bb3a-4edf-ad07-7fe65227f087.pdf"},{"id":14547068,"mime":"application/pdf","name":"Легион. Урок 39. Дз.pdf","extension":"pdf","link":"https://storage.yandexcloud.net/topschool.backet/public/content_file/cc925068-2248-4d21-8d27-e972ea757b3f.pdf"}],"properties":{"is_button":true}}}]}